mcp_redis_airnet/__init__.py
mcp_redis_airnet/__main__.py
mcp_redis_airnet/py.typed
mcp_redis_airnet/server.py
mcp_redis_airnet-1.1.1.dist-info/METADATA
mcp_redis_airnet-1.1.1.dist-info/WHEEL
mcp_redis_airnet-1.1.1.dist-info/entry_points.txt
mcp_redis_airnet-1.1.1.dist-info/RECORD
