Metadata-Version: 2.4
Name: mcp-redis-airnet
Version: 1.1.1
Summary: Use for AinrNet Redis,add 'info' tool
Author-email: mi_zy <mi_zy@sina.com>
Requires-Python: >=3.12
Requires-Dist: mcp[cli]>=1.4.1
Requires-Dist: pydantic-settings>=2.8.1
Requires-Dist: redis>=5.0.2
